LICENSE
README.md
pyproject.toml
setup.py
pybazel/__init__.py
pybazel/__init__.pyi
pybazel/client.py
pybazel/client.pyi
pybazel/errors.py
pybazel/errors.pyi
pybazel/models.pyi
pybazel/utils.pyi
pybazel/version.py
pybazel/version.pyi
pybazel.egg-info/PKG-INFO
pybazel.egg-info/SOURCES.txt
pybazel.egg-info/dependency_links.txt
pybazel.egg-info/requires.txt
pybazel.egg-info/top_level.txt
pybazel/models/__init__.py
pybazel/models/__init__.pyi
pybazel/models/info.py
pybazel/models/info.pyi
pybazel/models/label.py
pybazel/models/label.pyi
pybazel/utils/__init__.py
pybazel/utils/__init__.pyi
pybazel/utils/logger.py
pybazel/utils/logger.pyi