Metadata-Version: 2.1
Name: pybazel
Version: 0.5.3
Summary: A python client for Bazel
Home-page: https://github.com/jmelahman/pybazel
Download-URL: https://github.com/jmelahman/pybazel/archive/refs/tags/v0.5.3.tar.gz
Author: Jamison Lahman
Author-email: jamison@lahman.dev
License: MIT
Keywords: bazel,bazelbuild,buildtools,tools
Classifier: Development Status :: 3 - Alpha
Classifier: License :: OSI Approved :: MIT License
Classifier: Operating System :: Unix
Classifier: Topic :: System :: Software Distribution
Classifier: Programming Language :: Python :: 3
Classifier: Programming Language :: Python :: 3.7
Classifier: Programming Language :: Python :: 3.8
Classifier: Programming Language :: Python :: 3.9
Classifier: Programming Language :: Python :: 3.10
Requires-Python: >=3.7
License-File: LICENSE
